top2vec/__init__.py
top2vec/embedding.py
top2vec/top2vec.py
top2vec-1.0.36.dist-info/LICENSE
top2vec-1.0.36.dist-info/METADATA
top2vec-1.0.36.dist-info/WHEEL
top2vec-1.0.36.dist-info/top_level.txt
top2vec-1.0.36.dist-info/RECORD
