Metadata-Version: 2.1
Name: top2vec
Version: 1.0.36
Summary: Top2Vec learns jointly embedded topic, document and word vectors.
Home-page: https://github.com/ddangelov/Top2Vec
Author: Dimo Angelov
Author-email: dimo.angelov@gmail.com
License: BSD
Keywords: topic modeling semantic search word document embedding
Classifier: Development Status :: 3 - Alpha
Classifier: Programming Language :: Python :: 3
Classifier: Intended Audience :: Science/Research
Classifier: Intended Audience :: Developers
Classifier: Topic :: Scientific/Engineering :: Artificial Intelligence
Classifier: Topic :: Scientific/Engineering :: Information Analysis
Classifier: License :: OSI Approved :: BSD License
Classifier: Operating System :: OS Independent
Requires-Python: >=3.10
License-File: LICENSE
Requires-Dist: numpy (>=1.20.0)
Requires-Dist: pandas
Requires-Dist: scikit-learn (>=1.2.0)
Requires-Dist: gensim (>=4.0.0)
Requires-Dist: umap-learn (>=0.5.1)
Requires-Dist: hdbscan (>=0.8.27)
Requires-Dist: wordcloud
Requires-Dist: transformers
Requires-Dist: tqdm
Provides-Extra: indexing
Requires-Dist: hnswlib ; extra == 'indexing'
Provides-Extra: sentence_encoders
Requires-Dist: tensorflow ; extra == 'sentence_encoders'
Requires-Dist: tensorflow-hub ; extra == 'sentence_encoders'
Requires-Dist: tensorflow-text ; extra == 'sentence_encoders'
Provides-Extra: sentence_transformers
Requires-Dist: torch ; extra == 'sentence_transformers'
Requires-Dist: sentence-transformers ; extra == 'sentence_transformers'
